tensorwrap/__init__.py
tensorwrap/config.py
tensorwrap/data.py
tensorwrap/module.py
tensorwrap/ops.py
tensorwrap/test.py
tensorwrap/version.py
tensorwrap/core/__init__.py
tensorwrap/core/losses/__init__.py
tensorwrap/core/losses/categorical.py
tensorwrap/core/losses/mean.py
tensorwrap/experimental/__init__.py
tensorwrap/experimental/serialize.py
tensorwrap/experimental/wrappers.py
tensorwrap/experimental/data/__init__.py
tensorwrap/experimental/data/arraybased.py
tensorwrap/nn/__init__.py
tensorwrap/nn/callbacks.py
tensorwrap/nn/checkpoints.py
tensorwrap/nn/activations/__init__.py
tensorwrap/nn/activations/base.py
tensorwrap/nn/initializers/__init__.py
tensorwrap/nn/initializers/base.py
tensorwrap/nn/layers/__init__.py
tensorwrap/nn/layers/base.py
tensorwrap/nn/layers/lambda_layers.py
tensorwrap/nn/losses/__init__.py
tensorwrap/nn/losses/base.py
tensorwrap/nn/losses/categorical.py
tensorwrap/nn/losses/mean.py
tensorwrap/nn/losses/metrics.py
tensorwrap/nn/models/__init__.py
tensorwrap/nn/models/base.py
tensorwrap/nn/models/train.py
tensorwrap/nn/optimizers/__init__.py
tensorwrap/nn/optimizers/base.py
tensorwrap-0.0.1.5.dist-info/LICENSE
tensorwrap-0.0.1.5.dist-info/METADATA
tensorwrap-0.0.1.5.dist-info/WHEEL
tensorwrap-0.0.1.5.dist-info/top_level.txt
tensorwrap-0.0.1.5.dist-info/RECORD
